cppquant/__init__.py
cppquant/args_handler.py
cppquant/census_util.py
cppquant/dclass.py
cppquant/fasta_util.py
cppquant/imputer.py
cppquant/main.py
cppquant/ratio_rollup.py
cppquant/uncertainty_estimation.py
cppquant/util.py
cppquant-0.0.2.dist-info/METADATA
cppquant-0.0.2.dist-info/WHEEL
cppquant-0.0.2.dist-info/entry_points.txt
cppquant-0.0.2.dist-info/top_level.txt
cppquant-0.0.2.dist-info/RECORD
