Metadata-Version: 2.1
Name: cppquant
Version: 0.0.2
Summary: Simple tool to compare cpp quant results
Author-email: Patrick Garrett <pgarrett@scripps.edu>
Classifier: Programming Language :: Python :: 3
Classifier: Development Status :: 4 - Beta
Classifier: License :: OSI Approved :: MIT License
Classifier: Operating System :: OS Independent
Requires-Python: >=3.9
Requires-Dist: numpy
Requires-Dist: pandas
Requires-Dist: peptacular ==2.0.0
Requires-Dist: statsmodels
Requires-Dist: regex
Requires-Dist: scipy
Requires-Dist: setuptools
Requires-Dist: argparse
